bubbletea_chat/__init__.py
bubbletea_chat/components.py
bubbletea_chat/decorators.py
bubbletea_chat/llm.py
bubbletea_chat/schemas.py
bubbletea_chat/server.py
bubbletea_chat-0.6.4.dist-info/METADATA
bubbletea_chat-0.6.4.dist-info/WHEEL
bubbletea_chat-0.6.4.dist-info/top_level.txt
bubbletea_chat-0.6.4.dist-info/RECORD
