Metadata-Version: 2.4
Name: bubbletea-chat
Version: 0.6.4
Summary: A Python package for building AI chatbots with LiteLLM support for BubbleTea platform
Home-page: https://github.com/bubbletea/bubbletea-python
Author: BubbleTea Team
Author-email: BubbleTea Team <team@bubbletea.dev>
License: MIT
Project-URL: Homepage, https://bubbletea.dev
Project-URL: Documentation, https://docs.bubbletea.dev
Project-URL: Repository, https://github.com/bubbletea/bubbletea-python
Keywords: chatbot,ai,bubbletea,conversational-ai
Classifier: Development Status :: 3 - Alpha
Classifier: Intended Audience :: Developers
Classifier: License :: OSI Approved :: MIT License
Classifier: Programming Language :: Python :: 3
Classifier: Programming Language :: Python :: 3.8
Classifier: Programming Language :: Python :: 3.9
Classifier: Programming Language :: Python :: 3.10
Classifier: Programming Language :: Python :: 3.11
Requires-Python: >=3.8
Requires-Dist: fastapi>=0.100.0
Requires-Dist: uvicorn>=0.23.0
Requires-Dist: pydantic>=2.0.0
Provides-Extra: llm
Requires-Dist: litellm>=1.0.0; extra == "llm"
Dynamic: author
Dynamic: home-page
Dynamic: requires-python
